{
  "total_count": 1,
  "jobs": [
    {
      "id": 80049182359,
      "run_id": 27124418593,
      "workflow_name": "Frontend Deploy to Vercel",
      "head_branch": "main",
      "run_url": "https://api.github.com/repos/YhonatanQU/KP-FERRE/actions/runs/27124418593",
      "run_attempt": 1,
      "node_id": "CR_kwDOS0JY3s8AAAASo02Wlw",
      "head_sha": "643fb6615ed74fead638bbd109603ae245b6eb53",
      "url": "https://api.github.com/repos/YhonatanQU/KP-FERRE/actions/jobs/80049182359",
      "html_url": "https://github.com/YhonatanQU/KP-FERRE/actions/runs/27124418593/job/80049182359",
      "status": "completed",
      "conclusion": "failure",
      "created_at": "2026-06-08T08:09:40Z",
      "started_at": "2026-06-08T08:09:45Z",
      "completed_at": "2026-06-08T08:10:29Z",
      "name": "Deploy frontend to Vercel",
      "steps": [
        {
          "name": "Set up job",
          "status": "completed",
          "conclusion": "success",
          "number": 1,
          "started_at": "2026-06-08T08:09:45Z",
          "completed_at": "2026-06-08T08:09:46Z"
        },
        {
          "name": "Checkout repo",
          "status": "completed",
          "conclusion": "success",
          "number": 2,
          "started_at": "2026-06-08T08:09:46Z",
          "completed_at": "2026-06-08T08:09:47Z"
        },
        {
          "name": "Setup Node.js",
          "status": "completed",
          "conclusion": "success",
          "number": 3,
          "started_at": "2026-06-08T08:09:47Z",
          "completed_at": "2026-06-08T08:09:52Z"
        },
        {
          "name": "Install dependencies",
          "status": "completed",
          "conclusion": "success",
          "number": 4,
          "started_at": "2026-06-08T08:09:52Z",
          "completed_at": "2026-06-08T08:10:05Z"
        },
        {
          "name": "Build frontend",
          "status": "completed",
          "conclusion": "success",
          "number": 5,
          "started_at": "2026-06-08T08:10:05Z",
          "completed_at": "2026-06-08T08:10:11Z"
        },
        {
          "name": "Install Vercel CLI",
          "status": "completed",
          "conclusion": "success",
          "number": 6,
          "started_at": "2026-06-08T08:10:11Z",
          "completed_at": "2026-06-08T08:10:25Z"
        },
        {
          "name": "Configure Vercel project",
          "status": "completed",
          "conclusion": "success",
          "number": 7,
          "started_at": "2026-06-08T08:10:25Z",
          "completed_at": "2026-06-08T08:10:26Z"
        },
        {
          "name": "Deploy to Vercel",
          "status": "completed",
          "conclusion": "failure",
          "number": 8,
          "started_at": "2026-06-08T08:10:26Z",
          "completed_at": "2026-06-08T08:10:27Z"
        },
        {
          "name": "Show Vercel deployment URL",
          "status": "completed",
          "conclusion": "skipped",
          "number": 9,
          "started_at": "2026-06-08T08:10:27Z",
          "completed_at": "2026-06-08T08:10:27Z"
        },
        {
          "name": "Post Setup Node.js",
          "status": "completed",
          "conclusion": "skipped",
          "number": 17,
          "started_at": "2026-06-08T08:10:27Z",
          "completed_at": "2026-06-08T08:10:27Z"
        },
        {
          "name": "Post Checkout repo",
          "status": "completed",
          "conclusion": "success",
          "number": 18,
          "started_at": "2026-06-08T08:10:27Z",
          "completed_at": "2026-06-08T08:10:27Z"
        },
        {
          "name": "Complete job",
          "status": "completed",
          "conclusion": "success",
          "number": 19,
          "started_at": "2026-06-08T08:10:27Z",
          "completed_at": "2026-06-08T08:10:27Z"
        }
      ],
      "check_run_url": "https://api.github.com/repos/YhonatanQU/KP-FERRE/check-runs/80049182359",
      "labels": [
        "ubuntu-latest"
      ],
      "runner_id": 1000000028,
      "runner_name": "GitHub Actions 1000000028",
      "runner_group_id": 0,
      "runner_group_name": "GitHub Actions"
    }
  ]
}
